{
   "surname": "Swinson", 
   "twitter": "joswinson", 
   "town_of_birth": "Glasgow", 
   "companies_house": [], 
   "mp_gifts": 0, 
   "keywords": [
      "Jo", 
      "Swinson", 
      "East Dunbartonshire", 
      "Liberal Democrat", 
      "", 
      "Mental", 
      "Illness,", 
      "Departmental", 
      "Manpower,", 
      "Embassies,", 
      "Departmental", 
      "Televisions,", 
      "Mental", 
      "Health", 
      "Foreign", 
      "and", 
      "Commonwealth", 
      "Affairs,", 
      "Home", 
      "Department,", 
      "Treasury,", 
      "Health,", 
      "Work", 
      "and", 
      "Pensions", 
      "Foreign", 
      "affairs,", 
      "political", 
      "engagement,", 
      "quality", 
      "of", 
      "life", 
      "and", 
      "wellbeing,", 
      "climate", 
      "change,", 
      "allergy,", 
      "body", 
      "image", 
      "Chechnya,", 
      "India,", 
      "Kosovo,", 
      "Romania,", 
      "Sierra", 
      "Leone", 
      "Environmental", 
      "Audit", 
      "Committee"
   ], 
   "mp_income": 74962, 
   "biography_entries": [
      "Foreign affairs, political engagement, quality of life and wellbeing, climate change, allergy, body image", 
      "Chechnya, India, Kosovo, Romania, Sierra Leone"
   ], 
   "mp_donations": 57111, 
   "wrans_departments": "Foreign and Commonwealth Affairs, Home Department, Treasury, Health, Work and Pensions", 
   "person_id": "11971", 
   "party": "Liberal Democrat", 
   "forname": "Jo", 
   "mp_annual": 132073, 
   "mp_wealth": 15, 
   "facebook": "https://facebook.com/joswinson", 
   "eu_ref_stance": "", 
   "categories": [
      {
         "items": [], 
         "isCurrency": true, 
         "category_gifts": 0, 
         "category_type": "employment", 
         "category_income": 0, 
         "raw_items": [
            "30 June 2017, received \u00a31,550 for reviewing papers and providing advice as a member of the Advertising Advisory Committee of the Advertising Standards Authority, 71 High Holborn, London WC1V 6QT. Hours: none since my election. I have now resigned. I consulted ACoBA about this appointment. (Registered 07 July 2017)"
         ], 
         "category_description": "Private Employment", 
         "category_id": 1, 
         "category_amount": 0, 
         "category_donations": 0, 
         "category_wealth": 0
      }, 
      {
         "items": [
            {
               "raw_string": "Name of donor: Keith MoodyAddress of donor: privateAmount of donation or nature and value if donation in kind: \u00a31,000Donor status: individual(Registered 07 July 2017)", 
               "status": "individual", 
               "isWealth": false, 
               "nouns": [], 
               "isDonation": true, 
               "registered": "07/07/2017", 
               "isIncome": false, 
               "amount": 1000, 
               "pretty": "Keith Moody", 
               "address": "private", 
               "item_id": "0001", 
               "donor": "Keith Moody", 
               "category_id": 2, 
               "isGift": false
            }, 
            {
               "raw_string": "Name of donor: Keith MoodyAddress of donor: privateAmount of donation or nature and value if donation in kind: \u00a31,111Donor status: individual(Registered 07 July 2017)", 
               "status": "individual", 
               "isWealth": false, 
               "nouns": [], 
               "isDonation": true, 
               "registered": "07/07/2017", 
               "isIncome": false, 
               "amount": 1111, 
               "pretty": "Keith Moody", 
               "address": "private", 
               "item_id": "0002", 
               "donor": "Keith Moody", 
               "category_id": 2, 
               "isGift": false
            }, 
            {
               "raw_string": "Name of donor: Ghill DonaldAddress of donor: privateAmount of donation or nature and value if donation in kind: \u00a32,000Donor status: individual(Registered 07 July 2017)", 
               "status": "individual", 
               "isWealth": false, 
               "nouns": [], 
               "isDonation": true, 
               "registered": "07/07/2017", 
               "isIncome": false, 
               "amount": 2000, 
               "pretty": "Ghill Donald", 
               "address": "private", 
               "item_id": "0003", 
               "donor": "Ghill Donald", 
               "category_id": 2, 
               "isGift": false
            }, 
            {
               "raw_string": "Name of donor: Dinesh DhamijaAddress of donor: privateAmount of donation or nature and value if donation in kind: \u00a35,000Donor status: individual(Registered 07 July 2017)", 
               "status": "individual", 
               "isWealth": false, 
               "nouns": [], 
               "isDonation": true, 
               "registered": "07/07/2017", 
               "isIncome": false, 
               "amount": 5000, 
               "pretty": "Dinesh Dhamija", 
               "address": "private", 
               "item_id": "0004", 
               "donor": "Dinesh Dhamija", 
               "category_id": 2, 
               "isGift": false
            }, 
            {
               "raw_string": "Name of donor: Mark PettersonAddress of donor: privateAmount of donation or nature and value if donation in kind: \u00a310,000Donor status: individual(Registered 07 July 2017)", 
               "status": "individual", 
               "isWealth": false, 
               "nouns": [], 
               "isDonation": true, 
               "registered": "07/07/2017", 
               "isIncome": false, 
               "amount": 10000, 
               "pretty": "Mark Petterson", 
               "address": "private", 
               "item_id": "0005", 
               "donor": "Mark Petterson", 
               "category_id": 2, 
               "isGift": false
            }, 
            {
               "raw_string": "Name of donor: Michelle QuestAddress of donor: privateAmount of donation or nature and value if donation in kind: \u00a35,000Donor status: individual(Registered 07 July 2017)", 
               "status": "individual", 
               "isWealth": false, 
               "nouns": [], 
               "isDonation": true, 
               "registered": "07/07/2017", 
               "isIncome": false, 
               "amount": 5000, 
               "pretty": "Michelle Quest", 
               "address": "private", 
               "item_id": "0006", 
               "donor": "Michelle Quest", 
               "category_id": 2, 
               "isGift": false
            }, 
            {
               "raw_string": "Name of donor: Alistair BarrAddress of donor: privateAmount of donation or nature and value if donation in kind: \u00a35,000Donor status: individual(Registered 07 July 2017)", 
               "status": "individual", 
               "isWealth": false, 
               "nouns": [], 
               "isDonation": true, 
               "registered": "07/07/2017", 
               "isIncome": false, 
               "amount": 5000, 
               "pretty": "Alistair Barr", 
               "address": "private", 
               "item_id": "0007", 
               "donor": "Alistair Barr", 
               "category_id": 2, 
               "isGift": false
            }, 
            {
               "raw_string": "Name of donor: More UnitedAddress of donor: 49 Knatchbull Road, London SE5 9QRAmount of donation or nature and value if donation in kind: \u00a33,000Donor status: company, registration 10285790(Registered 07 July 2017)", 
               "status": "company, registration 10285790", 
               "isWealth": false, 
               "nouns": [], 
               "isDonation": true, 
               "registered": "07/07/2017", 
               "isIncome": false, 
               "amount": 3000, 
               "pretty": "More United", 
               "address": "49 Knatchbull Road, London SE5 9QR", 
               "item_id": "0008", 
               "donor": "More United", 
               "category_id": 2, 
               "isGift": false
            }, 
            {
               "raw_string": "Name of donor: Lord Matthew OakeshottAddress of donor: privateAmount of donation or nature and value if donation in kind: \u00a310,000Donor status: individual(Registered 07 July 2017)", 
               "status": "individual", 
               "isWealth": false, 
               "nouns": [], 
               "isDonation": true, 
               "registered": "07/07/2017", 
               "isIncome": false, 
               "amount": 10000, 
               "pretty": "Lord Matthew Oakeshott", 
               "address": "private", 
               "item_id": "0009", 
               "donor": "Lord Matthew Oakeshott", 
               "category_id": 2, 
               "isGift": false
            }, 
            {
               "raw_string": "Name of donor: Andrew DixonAddress of donor: privateAmount of donation or nature and value if donation in kind: \u00a310,000Donor status: individual(Registered 07 July 2017)", 
               "status": "individual", 
               "isWealth": false, 
               "nouns": [], 
               "isDonation": true, 
               "registered": "07/07/2017", 
               "isIncome": false, 
               "amount": 10000, 
               "pretty": "Andrew Dixon", 
               "address": "private", 
               "item_id": "0010", 
               "donor": "Andrew Dixon", 
               "category_id": 2, 
               "isGift": false
            }, 
            {
               "raw_string": "Name of donor: Joe Zammit-LuciaAddress of donor: privateAmount of donation or nature and value if donation in kind: \u00a35,000Donor status: individual(Registered 07 July 2017)", 
               "status": "individual", 
               "isWealth": false, 
               "nouns": [], 
               "isDonation": true, 
               "registered": "07/07/2017", 
               "isIncome": false, 
               "amount": 5000, 
               "pretty": "Joe Zammit-Lucia", 
               "address": "private", 
               "item_id": "0011", 
               "donor": "Joe Zammit-Lucia", 
               "category_id": 2, 
               "isGift": false
            }
         ], 
         "isCurrency": true, 
         "category_gifts": 0, 
         "category_type": "indirect_donations", 
         "category_income": 0, 
         "raw_items": [
            "Name of donor: Keith MoodyAddress of donor: privateAmount of donation or nature and value if donation in kind: \u00a31,000Donor status: individual(Registered 07 July 2017)", 
            "Name of donor: Keith MoodyAddress of donor: privateAmount of donation or nature and value if donation in kind: \u00a31,111Donor status: individual(Registered 07 July 2017)", 
            "Name of donor: Ghill DonaldAddress of donor: privateAmount of donation or nature and value if donation in kind: \u00a32,000Donor status: individual(Registered 07 July 2017)", 
            "Name of donor: Dinesh DhamijaAddress of donor: privateAmount of donation or nature and value if donation in kind: \u00a35,000Donor status: individual(Registered 07 July 2017)", 
            "Name of donor: Mark PettersonAddress of donor: privateAmount of donation or nature and value if donation in kind: \u00a310,000Donor status: individual(Registered 07 July 2017)", 
            "Name of donor: Michelle QuestAddress of donor: privateAmount of donation or nature and value if donation in kind: \u00a35,000Donor status: individual(Registered 07 July 2017)", 
            "Name of donor: Alistair BarrAddress of donor: privateAmount of donation or nature and value if donation in kind: \u00a35,000Donor status: individual(Registered 07 July 2017)", 
            "Name of donor: More UnitedAddress of donor: 49 Knatchbull Road, London SE5 9QRAmount of donation or nature and value if donation in kind: \u00a33,000Donor status: company, registration 10285790(Registered 07 July 2017)", 
            "Name of donor: Lord Matthew OakeshottAddress of donor: privateAmount of donation or nature and value if donation in kind: \u00a310,000Donor status: individual(Registered 07 July 2017)", 
            "Name of donor: Andrew DixonAddress of donor: privateAmount of donation or nature and value if donation in kind: \u00a310,000Donor status: individual(Registered 07 July 2017)", 
            "Name of donor: Joe Zammit-LuciaAddress of donor: privateAmount of donation or nature and value if donation in kind: \u00a35,000Donor status: individual(Registered 07 July 2017)"
         ], 
         "category_description": "Indirect Donations", 
         "category_id": 2, 
         "category_amount": 57111, 
         "category_donations": 57111, 
         "category_wealth": 0
      }, 
      {
         "items": [], 
         "isCurrency": true, 
         "category_gifts": 0, 
         "category_type": "direct_donations", 
         "category_income": 0, 
         "raw_items": [], 
         "category_description": "Direct Donations", 
         "category_id": 3, 
         "category_amount": 0, 
         "category_donations": 0, 
         "category_wealth": 0
      }, 
      {
         "items": [], 
         "isCurrency": true, 
         "category_gifts": 0, 
         "category_type": "gifts", 
         "category_income": 0, 
         "raw_items": [], 
         "category_description": "Gifts", 
         "category_id": 4, 
         "category_amount": 0, 
         "category_donations": 0, 
         "category_wealth": 0
      }, 
      {
         "items": [], 
         "isCurrency": true, 
         "category_gifts": 0, 
         "category_type": "visits_outside_uk", 
         "category_income": 0, 
         "raw_items": [], 
         "category_description": "Vists Outside UK", 
         "category_id": 5, 
         "category_amount": 0, 
         "category_donations": 0, 
         "category_wealth": 0
      }, 
      {
         "items": [], 
         "isCurrency": true, 
         "category_gifts": 0, 
         "category_type": "gifts_outside_uk", 
         "category_income": 0, 
         "raw_items": [], 
         "category_description": "Gifts Outside UK", 
         "category_id": 6, 
         "category_amount": 0, 
         "category_donations": 0, 
         "category_wealth": 0
      }, 
      {
         "items": [], 
         "isCurrency": true, 
         "category_gifts": 0, 
         "category_type": "property", 
         "category_income": 0, 
         "raw_items": [], 
         "category_description": "Property", 
         "category_id": 7, 
         "category_amount": 0, 
         "category_donations": 0, 
         "category_wealth": 0
      }, 
      {
         "isCurrency": false, 
         "last": "swinson", 
         "items": [
            {
               "raw_string": "Equal Power Consulting Ltd; consultancy services, speaking and writing. Consulting and speaking activity ceased on my election to Parliament. The remaining activity will be the completion of a book commission. (Registered 07 July 2017)", 
               "isWealth": true, 
               "nouns": [], 
               "isDonation": false, 
               "registered": "07/07/2017", 
               "isIncome": false, 
               "amount": 15, 
               "link": "https://beta.companieshouse.gov.uk/company/09904913", 
               "pretty": "Equal Power Consulting Ltd; consultancy services, speaking and writing. Consulting and speaking activity ceased on my election to Parliament. The remaining activity will be the completion of a book commission.", 
               "item_id": "0001", 
               "category_id": 8, 
               "isGift": false, 
               "company": {
                  "company_status": "active", 
                  "can_file": true, 
                  "sic_codes": [
                     "70229", 
                     "90010", 
                     "90030"
                  ], 
                  "links": {
                     "filing_history": "/company/09904913/filing-history", 
                     "self": "/company/09904913", 
                     "officers": "/company/09904913/officers"
                  }, 
                  "registered_office_address": {
                     "country": "United Kingdom", 
                     "address_line_1": "71 - 75 Shelton Street", 
                     "postal_code": "WC2H 9JQ", 
                     "locality": "London"
                  }, 
                  "undeliverable_registered_office_address": false, 
                  "items": [], 
                  "jurisdiction": "england-wales", 
                  "confirmation_statement": {
                     "next_due": "2017-12-20", 
                     "last_made_up_to": "2016-12-06", 
                     "next_made_up_to": "2017-12-06", 
                     "overdue": false
                  }, 
                  "company_number": "09904913", 
                  "date_of_creation": "2015-12-07", 
                  "has_insolvency_history": false, 
                  "etag": "9a80acdb45166e842e0763bf06ac6d22df19c0a5", 
                  "accounts": {
                     "next_due": "2018-09-30", 
                     "next_made_up_to": "2017-12-31", 
                     "last_accounts": {
                        "period_start_on": "2015-12-07", 
                        "type": "total-exemption-small", 
                        "made_up_to": "2016-12-31", 
                        "period_end_on": "2016-12-31"
                     }, 
                     "next_accounts": {
                        "due_on": "2018-09-30", 
                        "period_start_on": "2017-01-01", 
                        "period_end_on": "2017-12-31", 
                        "overdue": false
                     }, 
                     "accounting_reference_date": {
                        "day": "31", 
                        "month": "12"
                     }, 
                     "overdue": false
                  }, 
                  "company_name": "EQUAL POWER CONSULTING LTD", 
                  "registered_office_is_in_dispute": false, 
                  "has_charges": false, 
                  "type": "ltd"
               }
            }
         ], 
         "category_description": "Shareholdings", 
         "category_gifts": 0, 
         "month": 2, 
         "middle": "kate", 
         "category_type": "shareholdings", 
         "category_wealth": 15, 
         "category_income": 0, 
         "raw_items": [
            "Equal Power Consulting Ltd; consultancy services, speaking and writing. Consulting and speaking activity ceased on my election to Parliament. The remaining activity will be the completion of a book commission. (Registered 07 July 2017)"
         ], 
         "year": 1980, 
         "category_id": 8, 
         "category_amount": 15, 
         "category_donations": 0, 
         "first": "joanne"
      }, 
      {
         "isCurrency": true, 
         "last": "swinson", 
         "items": [], 
         "category_description": "Other Shareholdings", 
         "category_gifts": 0, 
         "month": 2, 
         "middle": "kate", 
         "category_type": "shareholdings", 
         "category_wealth": 0, 
         "category_income": 0, 
         "raw_items": [], 
         "year": 1980, 
         "category_id": 9, 
         "category_amount": 0, 
         "category_donations": 0, 
         "first": "joanne"
      }, 
      {
         "items": [], 
         "isCurrency": false, 
         "category_gifts": 0, 
         "category_type": "miscellaneous", 
         "category_income": 0, 
         "raw_items": [], 
         "category_description": "Miscellaneous", 
         "category_id": 10, 
         "category_amount": 0, 
         "category_donations": 0, 
         "category_wealth": 0
      }, 
      {
         "items": [], 
         "isCurrency": false, 
         "category_gifts": 0, 
         "category_type": "family", 
         "category_income": 0, 
         "raw_items": [], 
         "category_description": "Family", 
         "category_id": 11, 
         "category_amount": 0, 
         "category_donations": 0, 
         "category_wealth": 0
      }, 
      {
         "items": [], 
         "isCurrency": false, 
         "category_gifts": 0, 
         "category_type": "family_lobbyists", 
         "category_income": 0, 
         "raw_items": [], 
         "category_description": "Family Lobbyists", 
         "category_id": 12, 
         "category_amount": 0, 
         "category_donations": 0, 
         "category_wealth": 0
      }, 
      {
         "isCurrency": true, 
         "forname": "Jo", 
         "surname": "Swinson", 
         "category_income": 74962, 
         "items": [
            {
               "raw_string": "Basic Salary", 
               "isWealth": false, 
               "nouns": [], 
               "isDonation": false, 
               "registered": null, 
               "isIncome": true, 
               "amount": 74962, 
               "pretty": "Basic Salary", 
               "item_id": "0001", 
               "category_id": 13, 
               "isGift": false
            }
         ], 
         "category_description": "Public Employment", 
         "category_gifts": 0, 
         "category_type": "salary", 
         "category_wealth": 0, 
         "offices": [
            {
               "dept": "", 
               "from_date": "2017-06-20", 
               "to_date": "9999-12-31", 
               "position": "Deputy Leader, Liberal Democrats"
            }
         ], 
         "chair_salary": 15025, 
         "panel_of_chairs_salary": 15025, 
         "entries": [], 
         "raw_entries": [], 
         "party": "Liberal Democrat", 
         "category_id": 13, 
         "category_amount": 74962, 
         "category_donations": 0, 
         "basic_salary": 74962
      }
   ], 
   "name": "Jo Swinson", 
   "dob": "February 1980", 
   "gender": "F", 
   "country_of_birth": "Scotland", 
   "wrans_subjects": "Mental Illness, Departmental Manpower, Embassies, Departmental Televisions, Mental Health", 
   "member_id": "41555", 
   "constituency": "East Dunbartonshire", 
   "commitees": [
      "Environmental Audit Committee"
   ]
}