{
   "dods_id": "77854", 
   "surname": "Jones", 
   "twitter": "darrenpjones", 
   "town_of_birth": "Bristol", 
   "companies_house": [], 
   "mp_gifts": 0, 
   "keywords": [
      "Darren", 
      "Jones", 
      "Bristol North West", 
      "Labour", 
      "", 
      "Pupils:", 
      "Personal", 
      "Records,", 
      "Alternative", 
      "Education,", 
      "Emergency", 
      "Services", 
      "Network,", 
      "Cars:", 
      "Loans,", 
      "UK", 
      "Membership", 
      "of", 
      "EU:", 
      "Referendums", 
      "Department", 
      "for", 
      "Education,", 
      "Cabinet", 
      "Office,", 
      "HM", 
      "Treasury,", 
      "Department", 
      "of", 
      "Health,", 
      "Department", 
      "for", 
      "Digital,", 
      "Culture,", 
      "Media", 
      "and", 
      "Sport", 
      "Science", 
      "and", 
      "Technology", 
      "Committee", 
      "(Commons)", 
      "European", 
      "Scrutiny", 
      "Committee"
   ], 
   "mp_income": 85346, 
   "mp_donations": 0, 
   "wrans_departments": "Department for Education, Cabinet Office, HM Treasury, Department of Health, Department for Digital, Culture, Media and Sport", 
   "person_id": "25637", 
   "party": "Labour", 
   "forname": "Darren", 
   "mp_annual": 85346, 
   "mp_wealth": 15, 
   "facebook": "https://facebook.com/darrenjonesmp", 
   "eu_ref_stance": "", 
   "categories": [
      {
         "items": [
            {
               "raw_string": "30 June 2017, received \u00a310,034.22 (salary and bonus payment), plus a car allowance of \u00a3400 and healthcare allowance of \u00a39.27, for my  work as a lawyer at British Telecommunications plc, during the course of the election campaign and, in addition, for one week after the Election. Address: 81 Newgate Street, London EC1A 7AJ. Hours: 7 hrs since my election. (Registered 05 July 2017; updated 18 July 2017)", 
               "isWealth": false, 
               "nouns": [], 
               "isDonation": false, 
               "registered": "05/07/2017", 
               "isIncome": true, 
               "amount": 10034, 
               "pretty": "30 June 2017, received \u00a310,034.22 (salary and bonus payment), plus a car allowance of \u00a3400 and healthcare allowance of \u00a39.27, for my  work as a lawyer at British Telecommunications plc, during the course of the election campaign and, in addition, for one week after the Election. Address: 81 Newgate Street, London EC1A 7AJ. Hours: 7 hrs since my election.", 
               "item_id": "0001", 
               "category_id": 1, 
               "isGift": false
            }, 
            {
               "raw_string": "21 August 2017, received \u00a3200 from Ipsos MORI, 3 Thomas More Square, London E1W 1YW, for a polling interview. Hours: 1 hr. (Registered 05 September 2017)", 
               "isWealth": false, 
               "nouns": [], 
               "isDonation": false, 
               "registered": "05/09/2017", 
               "isIncome": true, 
               "amount": 200, 
               "pretty": "21 August 2017, received \u00a3200 from Ipsos MORI, 3 Thomas More Square, London E1W 1YW, for a polling interview. Hours: 1 hr.", 
               "item_id": "0002", 
               "category_id": 1, 
               "isGift": false
            }, 
            {
               "raw_string": "29 September 2017, received \u00a3150 from ComRes, Four Millbank, London SW1P 3JA, for completing a survey. Hours: 30 mins. (Registered 20 October 2017)", 
               "isWealth": false, 
               "nouns": [], 
               "isDonation": false, 
               "registered": "20/10/2017", 
               "isIncome": true, 
               "amount": 150, 
               "pretty": "29 September 2017, received \u00a3150 from ComRes, Four Millbank, London SW1P 3JA, for completing a survey. Hours: 30 mins.", 
               "item_id": "0003", 
               "category_id": 1, 
               "isGift": false
            }
         ], 
         "isCurrency": true, 
         "category_gifts": 0, 
         "category_type": "employment", 
         "category_income": 10384, 
         "raw_items": [
            "30 June 2017, received \u00a310,034.22 (salary and bonus payment), plus a car allowance of \u00a3400 and healthcare allowance of \u00a39.27, for my  work as a lawyer at British Telecommunications plc, during the course of the election campaign and, in addition, for one week after the Election. Address: 81 Newgate Street, London EC1A 7AJ. Hours: 7 hrs since my election. (Registered 05 July 2017; updated 18 July 2017)", 
            "21 August 2017, received \u00a3200 from Ipsos MORI, 3 Thomas More Square, London E1W 1YW, for a polling interview. Hours: 1 hr. (Registered 05 September 2017)", 
            "From 3 October 2017 I am contracted to provide legal consultancy, via the office of Darren Jones Ltd, to Kemp Little LLP, 138 Cheapside, London EC2V 6BJ. (Registered 19 October 2017)", 
            "29 September 2017, received \u00a3150 from ComRes, Four Millbank, London SW1P 3JA, for completing a survey. Hours: 30 mins. (Registered 20 October 2017)"
         ], 
         "category_description": "Private Employment", 
         "category_id": 1, 
         "category_amount": 10384, 
         "category_donations": 0, 
         "category_wealth": 0
      }, 
      {
         "items": [], 
         "isCurrency": true, 
         "category_gifts": 0, 
         "category_type": "indirect_donations", 
         "category_income": 0, 
         "raw_items": [], 
         "category_description": "Indirect Donations", 
         "category_id": 2, 
         "category_amount": 0, 
         "category_donations": 0, 
         "category_wealth": 0
      }, 
      {
         "items": [], 
         "isCurrency": true, 
         "category_gifts": 0, 
         "category_type": "direct_donations", 
         "category_income": 0, 
         "raw_items": [], 
         "category_description": "Direct Donations", 
         "category_id": 3, 
         "category_amount": 0, 
         "category_donations": 0, 
         "category_wealth": 0
      }, 
      {
         "items": [], 
         "isCurrency": true, 
         "category_gifts": 0, 
         "category_type": "gifts", 
         "category_income": 0, 
         "raw_items": [], 
         "category_description": "Gifts", 
         "category_id": 4, 
         "category_amount": 0, 
         "category_donations": 0, 
         "category_wealth": 0
      }, 
      {
         "items": [], 
         "isCurrency": true, 
         "category_gifts": 0, 
         "category_type": "visits_outside_uk", 
         "category_income": 0, 
         "raw_items": [], 
         "category_description": "Vists Outside UK", 
         "category_id": 5, 
         "category_amount": 0, 
         "category_donations": 0, 
         "category_wealth": 0
      }, 
      {
         "items": [], 
         "isCurrency": true, 
         "category_gifts": 0, 
         "category_type": "gifts_outside_uk", 
         "category_income": 0, 
         "raw_items": [], 
         "category_description": "Gifts Outside UK", 
         "category_id": 6, 
         "category_amount": 0, 
         "category_donations": 0, 
         "category_wealth": 0
      }, 
      {
         "items": [], 
         "isCurrency": true, 
         "category_gifts": 0, 
         "category_type": "property", 
         "category_income": 0, 
         "raw_items": [], 
         "category_description": "Property", 
         "category_id": 7, 
         "category_amount": 0, 
         "category_donations": 0, 
         "category_wealth": 0
      }, 
      {
         "isCurrency": false, 
         "last": "jones", 
         "items": [
            {
               "raw_string": "Office of Darren Jones Ltd; legal consultancy. (Registered 05 July 2017)", 
               "isWealth": true, 
               "nouns": [], 
               "isDonation": false, 
               "registered": "05/07/2017", 
               "isIncome": false, 
               "amount": 15, 
               "link": "https://beta.companieshouse.gov.uk/company/10447527", 
               "pretty": "Office of Darren Jones Ltd; legal consultancy.", 
               "item_id": "0001", 
               "category_id": 8, 
               "isGift": false, 
               "company": {
                  "has_insolvency_history": false, 
                  "can_file": true, 
                  "sic_codes": [
                     "69102", 
                     "70210"
                  ], 
                  "links": {
                     "filing_history": "/company/10447527/filing-history", 
                     "self": "/company/10447527", 
                     "officers": "/company/10447527/officers", 
                     "persons_with_significant_control": "/company/10447527/persons-with-significant-control"
                  }, 
                  "registered_office_address": {
                     "address_line_2": "Covent Garden", 
                     "country": "England", 
                     "postal_code": "WC2H 9JQ", 
                     "locality": "London", 
                     "address_line_1": "71-75 Shelton Street"
                  }, 
                  "undeliverable_registered_office_address": false, 
                  "items": [], 
                  "jurisdiction": "england-wales", 
                  "company_number": "10447527", 
                  "date_of_creation": "2016-10-26", 
                  "confirmation_statement": {
                     "next_due": "2018-11-07", 
                     "last_made_up_to": "2017-10-24", 
                     "next_made_up_to": "2018-10-24", 
                     "overdue": false
                  }, 
                  "accounts": {
                     "next_due": "2019-07-31", 
                     "next_made_up_to": "2018-10-31", 
                     "last_accounts": {
                        "period_start_on": "2016-10-26", 
                        "type": "dormant", 
                        "made_up_to": "2017-10-31", 
                        "period_end_on": "2017-10-31"
                     }, 
                     "next_accounts": {
                        "due_on": "2019-07-31", 
                        "period_start_on": "2017-11-01", 
                        "period_end_on": "2018-10-31", 
                        "overdue": false
                     }, 
                     "accounting_reference_date": {
                        "day": "31", 
                        "month": "10"
                     }, 
                     "overdue": false
                  }, 
                  "company_name": "OFFICE OF DARREN JONES LIMITED", 
                  "company_status": "active", 
                  "previous_company_names": [
                     {
                        "effective_from": "2016-10-26", 
                        "ceased_on": "2017-06-20", 
                        "name": "BITDATA LIMITED"
                     }
                  ], 
                  "has_charges": false, 
                  "etag": "b341facc4cfb5836b1851a4ed8b737d97aa8d0d0", 
                  "type": "ltd", 
                  "registered_office_is_in_dispute": false
               }
            }
         ], 
         "category_description": "Shareholdings", 
         "category_gifts": 0, 
         "month": 11, 
         "middle": "paul", 
         "category_type": "shareholdings", 
         "category_wealth": 15, 
         "category_income": 0, 
         "raw_items": [
            "Office of Darren Jones Ltd; legal consultancy. (Registered 05 July 2017)"
         ], 
         "year": 1986, 
         "category_id": 8, 
         "category_amount": 15, 
         "category_donations": 0, 
         "first": "darren"
      }, 
      {
         "isCurrency": true, 
         "last": "jones", 
         "items": [], 
         "category_description": "Other Shareholdings", 
         "category_gifts": 0, 
         "month": 11, 
         "middle": "paul", 
         "category_type": "shareholdings", 
         "category_wealth": 0, 
         "category_income": 0, 
         "raw_items": [], 
         "year": 1986, 
         "category_id": 9, 
         "category_amount": 0, 
         "category_donations": 0, 
         "first": "darren"
      }, 
      {
         "items": [
            {
               "raw_string": "Director, currently unpaid, of the Office of Darren Jones Ltd. (Registered 19 October 2017)", 
               "isWealth": false, 
               "nouns": [], 
               "isDonation": false, 
               "registered": "19/10/2017", 
               "isIncome": false, 
               "amount": 0, 
               "pretty": "Director, currently unpaid, of the Office of Darren Jones Ltd.", 
               "item_id": "0001", 
               "category_id": 10, 
               "isGift": false
            }
         ], 
         "isCurrency": false, 
         "category_gifts": 0, 
         "category_type": "miscellaneous", 
         "category_income": 0, 
         "raw_items": [
            "Director, currently unpaid, of the Office of Darren Jones Ltd. (Registered 19 October 2017)"
         ], 
         "category_description": "Miscellaneous", 
         "category_id": 10, 
         "category_amount": 0, 
         "category_donations": 0, 
         "category_wealth": 0
      }, 
      {
         "items": [], 
         "isCurrency": false, 
         "category_gifts": 0, 
         "category_type": "family", 
         "category_income": 0, 
         "raw_items": [], 
         "category_description": "Family", 
         "category_id": 11, 
         "category_amount": 0, 
         "category_donations": 0, 
         "category_wealth": 0
      }, 
      {
         "items": [
            {
               "raw_string": "Until 4 July 2017, my wife, Lucy Symons, was a lobbyist for the Energy Tech Unit. (Registered 5 July 2017; updated 19 October 2017)", 
               "isWealth": false, 
               "nouns": [], 
               "isDonation": false, 
               "registered": "05/07/2017", 
               "isIncome": false, 
               "amount": null, 
               "pretty": "Until 4 July 2017, my wife, Lucy Symons, was a lobbyist for the Energy Tech Unit.", 
               "item_id": "0001", 
               "category_id": 12, 
               "isGift": false
            }
         ], 
         "isCurrency": false, 
         "category_gifts": 0, 
         "category_type": "family_lobbyists", 
         "category_income": 0, 
         "raw_items": [
            "Until 4 July 2017, my wife, Lucy Symons, was a lobbyist for the Energy Tech Unit. (Registered 5 July 2017; updated 19 October 2017)"
         ], 
         "category_description": "Family Lobbyists", 
         "category_id": 12, 
         "category_amount": 0, 
         "category_donations": 0, 
         "category_wealth": 0
      }, 
      {
         "isCurrency": true, 
         "forname": "Darren", 
         "surname": "Jones", 
         "category_income": 74962, 
         "items": [
            {
               "raw_string": "Basic Salary", 
               "isWealth": false, 
               "nouns": [], 
               "isDonation": false, 
               "registered": null, 
               "isIncome": true, 
               "amount": 74962, 
               "pretty": "Basic Salary", 
               "item_id": "0001", 
               "category_id": 13, 
               "isGift": false
            }
         ], 
         "category_description": "Public Employment", 
         "category_gifts": 0, 
         "category_type": "salary", 
         "category_wealth": 0, 
         "offices": [
            {
               "dept": "Science and Technology Committee (Commons)", 
               "from_date": "2017-09-11", 
               "to_date": "9999-12-31", 
               "position": "Member"
            }, 
            {
               "dept": "European Scrutiny Committee", 
               "from_date": "2017-10-30", 
               "to_date": "9999-12-31", 
               "position": "Member"
            }
         ], 
         "chair_salary": 15025, 
         "panel_of_chairs_salary": 15025, 
         "entries": [], 
         "raw_entries": [], 
         "party": "Labour", 
         "category_id": 13, 
         "category_amount": 74962, 
         "category_donations": 0, 
         "basic_salary": 74962
      }
   ], 
   "name": "Darren Jones", 
   "dob": "November 1986", 
   "gender": "M", 
   "country_of_birth": "England", 
   "wrans_subjects": "Pupils: Personal Records, Alternative Education, Emergency Services Network, Cars: Loans, UK Membership of EU: Referendums", 
   "member_id": "41586", 
   "constituency": "Bristol North West", 
   "commitees": [
      "Science and Technology Committee (Commons)", 
      "European Scrutiny Committee"
   ]
}