{"layout": {"hidesources": true, "autosize": true, "yaxis": {"showticklabels": false, "title": "", "showbackground": false, "showgrid": false, "zeroline": false, "showline": false}, "paper_bgcolor": "rgba(0,0,0,0)", "plot_bgcolor": "rgba(0,0,0,0)", "showlegend": false, "height": 619, "width": 1100, "xaxis": {"showticklabels": false, "title": "", "showbackground": false, "showgrid": false, "zeroline": false, "showline": false}, "hovermode": "closest", "margin": {"pad": 4, "r": 20, "b": 30, "t": 20, "l": 20}, "annotations": [{"xref": "paper", "yref": "paper", "text": "<a style=\"color: black; font-weight: 100; font-size: 12px;\">Data source: </a><a href=\"https://www.theyworkforyou.com/mp/10558#register\">theyworkforyou</a>, <a href=\"http://data.parliament.uk/membersdataplatform/memberquery.aspx\">parliament</a>", "y": 0, "x": 0, "font": {"size": 12}, "showarrow": false}, {"xref": "paper", "yref": "paper", "text": "<a style=\"color: black; font-weight: 100; font-size: 14px;\"><b>John Spellar,</b> Warley</a>", "y": 1, "x": 0.5, "font": {"color": "#444", "size": 14}, "showarrow": false}]}, "data": [{"opacity": 0.2, "name": "lines", "visible": true, "mode": "lines", "hoverinfo": "none", "y": [-1.101189841688471, -0.7460917681026829, null, -0.7460917681026829, -1.2202571101191815, null, -0.7460917681026829, -0.3670991469040127, null, -0.7460917681026829, 0.2856049728840013, null, -1.101189841688471, 0.11894236345433833, null, 0.11894236345433833, 1.0003933609290476, null, 0.11894236345433833, 0.9312066648361607, null, 0.11894236345433833, 1.295260558783777, null, -1.101189841688471, -2.404850497816842, null, -2.404850497816842, -2.6659192990268314, null, -2.404850497816842, -3.3857343852834103, null, -2.404850497816842, -2.4576248594399, null, -2.404850497816842, -3.480059659242815, null, -3.480059659242815, -4.65587577229039, null, -3.480059659242815, -3.973180867640286, null, -2.404850497816842, -3.32791927766775, null, -1.101189841688471, -0.9936814700687286, null, -0.9936814700687286, -1.776984255731143, null, -0.9936814700687286, -0.04203472149899425, null, -0.9936814700687286, -0.8543227277049668, null, -0.8543227277049668, -0.7400402246947, null], "x": [-2.318710946548891, -1.0901129233583484, null, -1.0901129233583484, -0.021471196404078716, null, -1.0901129233583484, 0.03139348273661648, null, -1.0901129233583484, -0.5272364722594829, null, -2.318710946548891, -2.3697892315173648, null, -2.3697892315173648, -1.591751570137949, null, -2.3697892315173648, -3.200415369974015, null, -2.3697892315173648, -2.4081584631617314, null, -2.318710946548891, -2.1529095609667417, null, -2.1529095609667417, -3.1525545101259524, null, -2.1529095609667417, -2.302798925820744, null, -2.1529095609667417, -1.144925431997833, null, -2.1529095609667417, -1.3743480204483196, null, -1.3743480204483196, -1.5346187536777671, null, -1.3743480204483196, -0.34818275234392565, null, -2.1529095609667417, -3.0234914152752195, null, -2.318710946548891, -3.6169717265234547, null, -3.6169717265234547, -4.441148862293122, null, -3.6169717265234547, -4.196872969934035, null, -3.6169717265234547, -4.840005421511807, null, -4.840005421511807, -5.944413307481987, null], "line": {"color": ["#b8bab8", "#b8bab8", "#b8bab8", "#b8bab8", "#b8bab8", "#b8bab8", "#b8bab8", "#b8bab8", "#b8bab8", "#b8bab8", "#b8bab8", "#b8bab8", "#b8bab8", "#b8bab8", "#b8bab8", "#b8bab8", "#b8bab8", "#b8bab8", "#b8bab8", "#b8bab8", "#b8bab8"], "width": 1}, "type": "scatter"}, {"textposition": "middle", "name": "nodes", "text": ["<b>John<br>Spellar", "<b>Miscellaneous</b>", "Miscellaneous", "Family", "Family Lobbyists", "<b>Wealth</b>", "Property", "Shareholdings", "Other Shareholdings", "<b>Freebies</b>", "Indirect Donations", "Direct Donations", "Gifts", "Vists Outside UK", "\u00a33,400", "\u00a31,319", "Gifts Outside UK", "<b>Income</b>", "Private Employment", "Rental Income", "Public Employment", "\u00a374,962"], "hovertext": ["John Spellar", "<b>Miscellaneous</b></br></br>\u00a30", "<b>Miscellaneous<br></b>\u00a30", "<b>Family<br></b>\u00a30", "<b>Family<br>Lobbyists<br></b>\u00a30", "<b>Wealth</b></br></br>\u00a30", "<b>Property<br></b>\u00a30", "<b>Shareholdings<br></b>\u00a30", "<b>Other<br>Shareholdings<br></b>\u00a30", "<b>Freebies</b></br></br>\u00a34,719", "<b>Indirect<br>Donations<br></b>\u00a30", "<b>Direct<br>Donations<br></b>\u00a30", "<b>Gifts<br></b>\u00a30", "<b>Vists<br>Outside<br>UK<br></b>\u00a34,719", "Tripartite Australia Israel UK Leadership Dialogue conference in Israel.", "Discussions on current situation in the Middle East and international involvement.", "<b>Gifts<br>Outside<br>UK<br></b>\u00a30", "<b>Income</b></br></br>\u00a374,962", "<b>Private<br>Employment<br></b>\u00a30", "<b>Rental<br>Income<br></b>\u00a30", "<b>Public<br>Employment<br></b>\u00a374,962", "Basic Salary"], "customdata": [null, null, null, null, null, null, null, null, null, null, null, null, null, null, null, null, null, null, null, null, null, null], "y": [-1.101189841688471, -0.7460917681026829, -1.2202571101191815, -0.3670991469040127, 0.2856049728840013, 0.11894236345433833, 1.0003933609290476, 0.9312066648361607, 1.295260558783777, -2.404850497816842, -2.6659192990268314, -3.3857343852834103, -2.4576248594399, -3.480059659242815, -4.65587577229039, -3.973180867640286, -3.32791927766775, -0.9936814700687286, -1.776984255731143, -0.04203472149899425, -0.8543227277049668, -0.7400402246947], "mode": "markers+text", "hoverinfo": "text", "marker": {"opacity": [1, 1, 1, 1, 1, 1, 1, 1, 1, 1, 1, 1, 1, 1, 0.9, 0.9, 1, 1, 1, 1, 1, 0.9], "colorscale": "Viridis", "color": ["#DC241f", "#ffbaf4", "#ffbaf4", "#ffbaf4", "#ffbaf4", "#b8bab8", "#b8bab8", "#b8bab8", "#b8bab8", "#fff570", "#fff570", "#fff570", "#fff570", "#fff570", "#fff899", "#fff899", "#fff570", "#f7a55d", "#f7a55d", "#f7a55d", "#f7a55d", "#fac99e"], "symbol": "dot", "line": {"color": "rgb(50,50,50)", "width": 0.5}, "size": [128, 60, 40, 40, 40, 60, 40, 40, 40, 60, 40, 40, 40, 40, 32, 30, 40, 60, 40, 40, 40, 130]}, "x": [-2.318710946548891, -1.0901129233583484, -0.021471196404078716, 0.03139348273661648, -0.5272364722594829, -2.3697892315173648, -1.591751570137949, -3.200415369974015, -2.4081584631617314, -2.1529095609667417, -3.1525545101259524, -2.302798925820744, -1.144925431997833, -1.3743480204483196, -1.5346187536777671, -0.34818275234392565, -3.0234914152752195, -3.6169717265234547, -4.441148862293122, -4.196872969934035, -4.840005421511807, -5.944413307481987], "type": "scatter"}]}